nb_llm_cache/__init__.py
nb_llm_cache/llm_cache.py
nb_llm_cache/db_integrations/__init__.py
nb_llm_cache/db_integrations/firestore_cache.py
nb_llm_cache/db_integrations/local_cache.py
nb_llm_cache-1.0.0.dist-info/LICENSE.md
nb_llm_cache-1.0.0.dist-info/METADATA
nb_llm_cache-1.0.0.dist-info/WHEEL
nb_llm_cache-1.0.0.dist-info/top_level.txt
nb_llm_cache-1.0.0.dist-info/RECORD
